{
  "shipType": "ENGI_SMALL_0",
  "wrecks": [
    {
      "texturePath": "texture/particle/wreck/small/engi_small0_wreck0.png",
      "fireTexturePath": "texture/particle/wreck/small/engi_small0_wreckfire0.png",
      "sparkleTexturePath": "texture/particle/wreck/small/engi_small0_wrecklight0.png",
      "vertices": [
        {
          "x": -1.68,
          "y": 2.02
        },
        {
          "x": -3.28,
          "y": 0.46
        },
        {
          "x": -3.2,
          "y": -1.14
        },
        {
          "x": -1.56,
          "y": -2.02
        },
        {
          "x": -0.04,
          "y": -1.9
        },
        {
          "x": -0.4,
          "y": 1.66
        }
      ]
    },
    {
      "texturePath": "texture/particle/wreck/small/engi_small0_wreck1.png",
      "fireTexturePath": "texture/particle/wreck/small/engi_small0_wreckfire1.png",
      "sparkleTexturePath": "texture/particle/wreck/small/engi_small0_wrecklight1.png",
      "vertices": [
        {
          "x": 1.4,
          "y": 1.34
        },
        {
          "x": -0.68,
          "y": -0.5
        },
        {
          "x": 0.76,
          "y": -2.1
        },
        {
          "x": 3.36,
          "y": -0.7
        },
        {
          "x": 3.44,
          "y": 0.26
        }
      ]
    }
  ]
}